PyConfigurer/__init__.py
PyConfigurer/main.py
pyconfigurer-0.1.1.dist-info/LICENSE
pyconfigurer-0.1.1.dist-info/WHEEL
pyconfigurer-0.1.1.dist-info/METADATA
pyconfigurer-0.1.1.dist-info/RECORD
