Metadata-Version: 2.1
Name: pyconfigurer
Version: 0.1.1
Summary: A GUI configuration library for python programs.
Home-page: https://github.com/ArjixWasTaken/PyConfigurer
License: MIT
Keywords: configuration,gui
Author: ArjixWasTaken
Requires-Python: >=3.6,<4.0
Classifier: License :: OSI Approved :: MIT License
Classifier: Operating System :: OS Independent
Classifier: Programming Language :: Python :: 3
Classifier: Programming Language :: Python :: 3.10
Classifier: Programming Language :: Python :: 3.6
Classifier: Programming Language :: Python :: 3.7
Classifier: Programming Language :: Python :: 3.8
Classifier: Programming Language :: Python :: 3.9
Requires-Dist: PySimpleGUI (>=4.55.1,<5.0.0)
Requires-Dist: toml (>=0.9,<0.10)
Project-URL: Repository, https://github.com/ArjixWasTaken/PyConfigurer
